catnip/__init__.py
catnip/apps.py
catnip/backend.py
catnip/exceptions.py
catnip/forms.py
catnip/middleware.py
catnip/models.py
catnip/tests.py
catnip/urls.py
catnip/user.py
catnip/views.py
catnip/migrations/0001_initial.py
catnip/migrations/__init__.py
catnip/static/css/style.css
catnip/static/css/catnip/catnip-dark.css
catnip/static/css/catnip/catnip-light.css
catnip/static/css/chartjs/Chart.min.css
catnip/static/css/font-awesome/all.css
catnip/static/css/font-awesome/all.min.css
catnip/static/css/font-awesome/brands.css
catnip/static/css/font-awesome/brands.min.css
catnip/static/css/font-awesome/fontawesome.css
catnip/static/css/font-awesome/fontawesome.min.css
catnip/static/css/font-awesome/regular.css
catnip/static/css/font-awesome/regular.min.css
catnip/static/css/font-awesome/solid.css
catnip/static/css/font-awesome/solid.min.css
catnip/static/css/font-awesome/svg-with-js.css
catnip/static/css/font-awesome/svg-with-js.min.css
catnip/static/css/font-awesome/v4-shims.css
catnip/static/css/font-awesome/v4-shims.min.css
catnip/static/css/taildatetime/tail.datetime-harx-dark.css
catnip/static/js/format-data.js
catnip/static/js/notification.js
catnip/static/js/service.js
catnip/static/js/url-manager.js
catnip/static/js/utils.js
catnip/static/js/vendor/chartjs/Chart.bundle.min.js
catnip/static/js/vendor/jquery/jquery-3.2.1.slim.min.js
catnip/static/js/vendor/popperjs/popper.min.js
catnip/static/js/vendor/taildatetime/tail.datetime.min.js
catnip/static/js/vendor/uikit/uikit-icons.js
catnip/static/js/vendor/uikit/uikit.js
catnip/static/js/vendor/vuejs/vue-resource@1.3.5.js
catnip/static/js/vendor/vuejs/vue-router.min.js
catnip/static/js/vendor/vuejs/vue.js
catnip/static/pictures/catnip_logo.png
catnip/static/pictures/favicon-16x16.png
catnip/static/pictures/favicon-32x32.png
catnip/static/pictures/favicon-96x96.png
catnip/static/vue/components/event-bus/event-bus.js
catnip/static/vue/components/filter/filter.js
catnip/static/vue/components/hashmap/hashmap-field.js
catnip-0.0.1.dist-info/LICENSE
catnip-0.0.1.dist-info/METADATA
catnip-0.0.1.dist-info/WHEEL
catnip-0.0.1.dist-info/top_level.txt
catnip-0.0.1.dist-info/RECORD
